[
  {
    "epoch": 0,
    "train_loss": 3.163242647724767,
    "val_loss": 2.7849512497584024,
    "elapsed_s": 0.59
  },
  {
    "epoch": 1,
    "train_loss": 2.3892368847324,
    "val_loss": 2.1450541019439697,
    "elapsed_s": 0.6
  },
  {
    "epoch": 2,
    "train_loss": 2.1308352485779793,
    "val_loss": 2.0304811696211496,
    "elapsed_s": 0.64
  },
  {
    "epoch": 3,
    "train_loss": 2.079292860723311,
    "val_loss": 2.0008879005908966,
    "elapsed_s": 0.57
  },
  {
    "epoch": 4,
    "train_loss": 2.0655377661028216,
    "val_loss": 1.995811919371287,
    "elapsed_s": 0.56
  }
]