[
  {
    "epoch": 0,
    "train_loss": 3.162701892852783,
    "val_loss": 2.8301960229873657,
    "elapsed_s": 0.99
  },
  {
    "epoch": 1,
    "train_loss": 2.509658069610596,
    "val_loss": 2.2175406217575073,
    "elapsed_s": 1.05
  },
  {
    "epoch": 2,
    "train_loss": 2.162307801246643,
    "val_loss": 2.086537698904673,
    "elapsed_s": 1.03
  },
  {
    "epoch": 3,
    "train_loss": 2.0966438484191894,
    "val_loss": 2.019356995820999,
    "elapsed_s": 1.04
  },
  {
    "epoch": 4,
    "train_loss": 2.0692855954170226,
    "val_loss": 2.0034748713175454,
    "elapsed_s": 1.08
  },
  {
    "epoch": 5,
    "train_loss": 2.05323979139328,
    "val_loss": 1.988365908463796,
    "elapsed_s": 1.0
  },
  {
    "epoch": 6,
    "train_loss": 2.0462397646903994,
    "val_loss": 2.0098631978034973,
    "elapsed_s": 0.99
  },
  {
    "epoch": 7,
    "train_loss": 2.0385011649131775,
    "val_loss": 1.98167089621226,
    "elapsed_s": 1.18
  },
  {
    "epoch": 8,
    "train_loss": 2.0189907646179197,
    "val_loss": 1.9788656930128734,
    "elapsed_s": 1.17
  },
  {
    "epoch": 9,
    "train_loss": 2.0110332417488097,
    "val_loss": 1.9720332026481628,
    "elapsed_s": 1.24
  },
  {
    "epoch": 10,
    "train_loss": 2.0059686064720155,
    "val_loss": 1.9727792938550313,
    "elapsed_s": 1.45
  },
  {
    "epoch": 11,
    "train_loss": 2.0029654788970945,
    "val_loss": 1.9756943881511688,
    "elapsed_s": 2.34
  },
  {
    "epoch": 12,
    "train_loss": 1.9972156119346618,
    "val_loss": 1.9737379054228466,
    "elapsed_s": 1.71
  },
  {
    "epoch": 13,
    "train_loss": 1.9919995832443238,
    "val_loss": 1.9689446091651917,
    "elapsed_s": 1.65
  },
  {
    "epoch": 14,
    "train_loss": 1.9867532992362975,
    "val_loss": 1.973323126633962,
    "elapsed_s": 1.56
  },
  {
    "epoch": 15,
    "train_loss": 1.980869116783142,
    "val_loss": 1.9640621542930603,
    "elapsed_s": 1.51
  },
  {
    "epoch": 16,
    "train_loss": 1.9761691522598266,
    "val_loss": 1.9655564328034718,
    "elapsed_s": 1.52
  },
  {
    "epoch": 17,
    "train_loss": 1.9617325615882875,
    "val_loss": 1.9795311292012532,
    "elapsed_s": 1.52
  },
  {
    "epoch": 18,
    "train_loss": 1.9659336733818054,
    "val_loss": 1.9771376351515453,
    "elapsed_s": 1.54
  },
  {
    "epoch": 19,
    "train_loss": 1.9590004539489747,
    "val_loss": 1.9806847671667736,
    "elapsed_s": 1.46
  },
  {
    "epoch": 20,
    "train_loss": 1.9550671911239623,
    "val_loss": 1.9875792264938354,
    "elapsed_s": 1.5
  },
  {
    "epoch": 21,
    "train_loss": 1.9454428696632384,
    "val_loss": 1.9842878977457683,
    "elapsed_s": 1.48
  },
  {
    "epoch": 22,
    "train_loss": 1.953350269794464,
    "val_loss": 1.9868898491064708,
    "elapsed_s": 1.46
  },
  {
    "epoch": 23,
    "train_loss": 1.9474433183670044,
    "val_loss": 1.9867885609467824,
    "elapsed_s": 1.48
  },
  {
    "epoch": 24,
    "train_loss": 1.9434439945220947,
    "val_loss": 1.9854501485824585,
    "elapsed_s": 1.49
  },
  {
    "epoch": 25,
    "train_loss": 1.945793902873993,
    "val_loss": 1.9890383382638295,
    "elapsed_s": 1.42
  },
  {
    "epoch": 26,
    "train_loss": 1.9401148295402526,
    "val_loss": 1.9893613557020824,
    "elapsed_s": 1.44
  },
  {
    "epoch": 27,
    "train_loss": 1.9360712146759034,
    "val_loss": 1.9904446701208751,
    "elapsed_s": 1.41
  },
  {
    "epoch": 28,
    "train_loss": 1.9379306054115295,
    "val_loss": 1.9903197487195332,
    "elapsed_s": 1.48
  },
  {
    "epoch": 29,
    "train_loss": 1.931942572593689,
    "val_loss": 1.9903689821561177,
    "elapsed_s": 1.42
  }
]